LICENSE.GPL
README.txt
setup.cfg
setup.py
tagger/NEXT.txt
tagger/PLAY.txt
tagger/RDF-HOWTO.txt
tagger/README.txt
tagger/__init__.py
tagger/dispatch_predicates.py
tagger/group.py
tagger/interfaces.py
tagger/tag.py
tagger/tests.py
tagger/utils.py
tagger.egg-info/PKG-INFO
tagger.egg-info/SOURCES.txt
tagger.egg-info/dependency_links.txt
tagger.egg-info/namespace_packages.txt
tagger.egg-info/requires.txt
tagger.egg-info/top_level.txt
tagger.egg-info/zip-safe
