Metadata-Version: 1.0
Name: tagger
Version: 0.2
Summary: Tagging Library utilizing rdflib
Home-page: http://www.openplans.org/projects/yucca/install-tagger
Author: Whit Morriss
Author-email: whit@openplans.org
License: GPL
Download-URL: http://www.openplans.org/projects/yucca/install-tagger
Platform: UNKNOWN
